auth/decorators.py
auth/jwt.py
auth/middleware.py
auth/remember.py
auth/integrations/authlib_adapter.py
background/backend.py
background/decorators.py
background/health.py
background/local.py
background/monitor.py
background/retry.py
cache/decorators.py
cache/etag.py
cache/backends/memory.py
cache/backends/redis.py
cli/.gitkeep
cli/__init__.py
cli/__main__.py
core/.gitkeep
core/__init__.py
core/app.py
core/background.py
core/context.py
core/http.py
core/lifecycle.py
core/middleware.py
core/plugins.py
core/server.py
core/settings.py
core/endpoints/health.py
di/.gitkeep
di/__init__.py
di/binder.py
di/cache.py
di/dependency.py
di/lifecycle.py
di/openapi.py
di/resolver.py
di/testing.py
di/typing.py
errors/converters.py
errors/debug_pages.py
errors/handler.py
errors/http.py
errors/openapi.py
errors/register.py
errors/reporting.py
errors/scrub.py
middleware/.gitkeep
middleware/__init__.py
middleware/background.py
middleware/context.py
middleware/trace.py
pacificpy-0.0.1.dist-info/licenses/LICENSE
plugins/.gitkeep
plugins/__init__.py
plugins/redis_client.py
plugins/sqlalchemy_plugin.py
plugins/tortoise_plugin.py
routing/.gitkeep
routing/__init__.py
routing/autodiscover.py
routing/decorators.py
routing/matcher.py
routing/meta.py
routing/method_infer.py
routing/params.py
routing/route.py
routing/router.py
security/.gitkeep
security/__init__.py
security/cors.py
security/csp.py
security/csrf.py
security/defaults.py
security/headers.py
security/rate_limit.py
security/xss.py
sessions/base.py
sessions/cookie.py
sessions/redis.py
templates/.gitkeep
templates/__init__.py
templates/components.py
templates/context.py
templates/dev.py
templates/engine.py
templates/filters.py
templates/forms.py
templates/static.py
validation/config.py
validation/di_integration.py
validation/errors.py
validation/files.py
validation/helpers.py
validation/params.py
validation/request.py
validation/response.py
pacificpy-0.0.1.dist-info/METADATA
pacificpy-0.0.1.dist-info/WHEEL
pacificpy-0.0.1.dist-info/top_level.txt
pacificpy-0.0.1.dist-info/RECORD
