Metadata-Version: 2.4
Name: pacificpy
Version: 0.0.1
Summary: A Python web framework for building scalable and maintainable web applications.
Home-page: https://github.com/dChicago/PacificPy
Author: David Konev
Author-email: David Konev <konevdavid769@gmail.com>
License: MIT License
Project-URL: Homepage, https://github.com/dChicago/PacificPy
Project-URL: Repository, https://github.com/dChicago/PacificPy.git
Project-URL: Issues, https://github.com/dChicago/PacificPy/issues
Keywords: web,framework,async,python
Classifier: Development Status :: 3 - Alpha
Classifier: Intended Audience :: Developers
Classifier: License :: OSI Approved :: MIT License
Classifier: Programming Language :: Python :: 3
Classifier: Programming Language :: Python :: 3.8
Classifier: Programming Language :: Python :: 3.9
Classifier: Programming Language :: Python :: 3.10
Classifier: Programming Language :: Python :: 3.11
Classifier: Programming Language :: Python :: 3.12
Requires-Python: >=3.8
License-File: LICENSE
Requires-Dist: aiohttp>=3.8.0
Requires-Dist: jinja2>=3.0.0
Requires-Dist: pydantic>=2.0.0
Provides-Extra: dev
Requires-Dist: pytest>=6.0; extra == "dev"
Requires-Dist: black>=21.0; extra == "dev"
Requires-Dist: flake8>=3.9; extra == "dev"
Requires-Dist: mypy>=0.900; extra == "dev"
Dynamic: author
Dynamic: home-page
Dynamic: license-file
Dynamic: requires-python
